staticflow/__init__.py
staticflow/admin/__init__.py
staticflow/admin/__pycache__/__init__.cpython-312.pyc
staticflow/admin/templates/base.html
staticflow/admin/templates/content.html
staticflow/admin/templates/index.html
staticflow/admin/templates/settings.html
staticflow/assets/__init__.py
staticflow/assets/manager.py
staticflow/cli/__init__.py
staticflow/cli/__pycache__/__init__.cpython-312.pyc
staticflow/cli/__pycache__/server.cpython-312.pyc
staticflow/cli/server.py
staticflow/core/__init__.py
staticflow/core/__pycache__/__init__.cpython-312.pyc
staticflow/core/__pycache__/cache.cpython-312.pyc
staticflow/core/__pycache__/config.cpython-312.pyc
staticflow/core/__pycache__/engine.cpython-312.pyc
staticflow/core/__pycache__/page.cpython-312.pyc
staticflow/core/__pycache__/site.cpython-312.pyc
staticflow/core/cache.py
staticflow/core/config.py
staticflow/core/engine.py
staticflow/core/page.py
staticflow/core/site.py
staticflow/parsers/__init__.py
staticflow/parsers/base.py
staticflow/parsers/html.py
staticflow/parsers/markdown.py
staticflow/plugins/__init__.py
staticflow/plugins/__pycache__/__init__.cpython-312.pyc
staticflow/plugins/__pycache__/base.cpython-312.pyc
staticflow/plugins/base.py
staticflow/plugins/builtin/__init__.py
staticflow/plugins/builtin/__pycache__/__init__.cpython-312.pyc
staticflow/plugins/builtin/__pycache__/minifier.cpython-312.pyc
staticflow/plugins/builtin/__pycache__/rss.cpython-312.pyc
staticflow/plugins/builtin/__pycache__/seo.cpython-312.pyc
staticflow/plugins/builtin/__pycache__/sitemap.cpython-312.pyc
staticflow/plugins/builtin/minifier.py
staticflow/plugins/builtin/rss.py
staticflow/plugins/builtin/seo.py
staticflow/plugins/builtin/sitemap.py
staticflow/plugins/core/__pycache__/base.cpython-312.pyc
staticflow/plugins/core/__pycache__/manager.cpython-312.pyc
staticflow/plugins/core/base.py
staticflow/plugins/core/manager.py
staticflow/plugins/diagrams.py
staticflow/plugins/math.py
staticflow/plugins/notion_blocks.py
staticflow-0.1.7.dist-info/entry_points.txt
staticflow-0.1.7.dist-info/METADATA
staticflow-0.1.7.dist-info/WHEEL
staticflow-0.1.7.dist-info/RECORD
